appstoreconnectapi/__init__.py
appstoreconnectapi/app.py
appstoreconnectapi-0.0.8.dist-info/METADATA
appstoreconnectapi-0.0.8.dist-info/WHEEL
appstoreconnectapi-0.0.8.dist-info/top_level.txt
appstoreconnectapi-0.0.8.dist-info/RECORD
