Metadata-Version: 2.1
Name: appstoreconnectapi
Version: 0.0.8
Summary: A Python wrapper around Apple AppStore Connect Api
Home-page: https://github.com/whdevlab/appstoreconnectapi
Author: WHDevLab
Author-email: whdevlab@163.com
License: MIT
Platform: UNKNOWN
Requires-Dist: requests
Requires-Dist: PyJWT
